aini/__init__.py
aini/builder.py
aini/listing.py
aini/viewer.py
aini/agno/agent.yml
aini/agno/models.yml
aini/agno/team.yml
aini/agno/tools.yml
aini/agno/workflow.yml
aini/autogen/assistant.yml
aini/autogen/client.yml
aini/autogen/context.yml
aini/autogen/llm.yml
aini/autogen/memory.yml
aini/autogen/team.yml
aini/autogen/userproxy.yml
aini/autogen/web_surfer.yml
aini/graph/langgraph.json
aini/lang/config.yml
aini/lang/graph.yml
aini/lang/llm.yml
aini/lang/memory.yml
aini/lang/msg.yml
aini/lang/react.yml
aini/lang/supervisor.yml
aini/lang/tools.yml
aini/lang_book/idea_validator.yml
aini/lang_book/validator.yml
aini/mem0/memory.yml
aini-0.3.3.dist-info/licenses/LICENSE
aini-0.3.3.dist-info/METADATA
aini-0.3.3.dist-info/WHEEL
aini-0.3.3.dist-info/top_level.txt
aini-0.3.3.dist-info/RECORD
