Metadata-Version: 2.4
Name: aini
Version: 0.3.3
Summary: Declarative AI components
Home-page: https://github.com/alpha-xone/aini
Author: Alpha x1
Author-email: Alpha x1 <alpha.xone@outlook.com>
Project-URL: Homepage, https://github.com/alpha-xone/aini
Project-URL: Bug Tracker, https://github.com/alpha-xone/aini/issues
Classifier: Programming Language :: Python :: 3
Classifier: License :: OSI Approved :: Apache Software License
Classifier: Operating System :: OS Independent
Requires-Python: >=3.7
License-File: LICENSE
Requires-Dist: rich>=13.0.0
Requires-Dist: pyyaml>=6.0.0
Requires-Dist: importlib-metadata>=6.0.0
Requires-Dist: typing-extensions>=4.0.0
Requires-Dist: pydantic>=2.11.0
Provides-Extra: agno
Requires-Dist: agno>=1.5.0; extra == "agno"
Provides-Extra: autogen
Requires-Dist: autogen-agentchat>=0.5.7; extra == "autogen"
Requires-Dist: autogen-core>=0.5.7; extra == "autogen"
Requires-Dist: autogen-ext>=0.5.7; extra == "autogen"
Provides-Extra: lang
Requires-Dist: langchain>=0.3.20; extra == "lang"
Requires-Dist: langchain-openai>=0.3.18; extra == "lang"
Requires-Dist: langchain-deepseek>=0.1.3; extra == "lang"
Requires-Dist: langgraph>=0.4.7; extra == "lang"
Provides-Extra: graph
Requires-Dist: langgraph-cli>=0.2.10; extra == "graph"
Requires-Dist: langgraph-api>=0.2.38; extra == "graph"
Requires-Dist: langchain>=0.3.20; extra == "graph"
Requires-Dist: langchain-openai>=0.3.18; extra == "graph"
Requires-Dist: langchain-deepseek>=0.1.3; extra == "graph"
Requires-Dist: langgraph>=0.4.7; extra == "graph"
Requires-Dist: langchain-tavily>=0.2.0; extra == "graph"
Provides-Extra: mem0
Requires-Dist: mem0ai>=0.1.104; extra == "mem0"
Requires-Dist: neo4j>=5.26.0; extra == "mem0"
Requires-Dist: langchain-neo4j>=0.4.0; extra == "mem0"
Requires-Dist: rank_bm25>=0.2.2; extra == "mem0"
Provides-Extra: all
Requires-Dist: agno>=1.5.0; extra == "all"
Requires-Dist: autogen-agentchat>=0.5.7; extra == "all"
Requires-Dist: autogen-core>=0.5.7; extra == "all"
Requires-Dist: autogen-ext>=0.5.7; extra == "all"
Requires-Dist: langchain>=0.3.20; extra == "all"
Requires-Dist: langchain-openai>=0.3.18; extra == "all"
Requires-Dist: langchain-deepseek>=0.1.3; extra == "all"
Requires-Dist: langgraph>=0.4.7; extra == "all"
Requires-Dist: langgraph-cli>=0.2.10; extra == "all"
Requires-Dist: langgraph-api>=0.2.38; extra == "all"
Requires-Dist: mem0ai>=0.1.104; extra == "all"
Requires-Dist: neo4j>=5.26.0; extra == "all"
Requires-Dist: langchain-neo4j>=0.4.0; extra == "all"
Requires-Dist: rank_bm25>=0.2.2; extra == "all"
Dynamic: author
Dynamic: home-page
Dynamic: license-file
Dynamic: requires-python
